README.rst
setup.cfg
setup.py
merge_acs_logs/__init__.py
merge_acs_logs.egg-info/PKG-INFO
merge_acs_logs.egg-info/SOURCES.txt
merge_acs_logs.egg-info/dependency_links.txt
merge_acs_logs.egg-info/entry_points.txt
merge_acs_logs.egg-info/requires.txt
merge_acs_logs.egg-info/top_level.txt