Metadata-Version: 1.2
Name: merge-acs-logs
Version: 0.0.1
Summary: just a small tool to merge log files of ACS by timestamp
Home-page: https://github.com/dneise/merge_acs_logs
Author: Dominik Neise
Author-email: neised@phys.ethz.ch
License: MIT
Platform: UNKNOWN
Requires-Python: >=3.6
